[
  { "query": "王楚钦2比3徐瑛彬", "display_query": "王楚钦2比3徐瑛彬" },
  {
    "query": "为什么父母会把两三万的学费非常当回事",
    "display_query": "为什么父母会把两三万的学费非常当回事"
  },
  {
    "query": "长的漂亮真的很有优势吗",
    "display_query": "长的漂亮真的很有优势吗"
  },
  {
    "query": "山东师范大学学生回宿舍要看 15 秒广告",
    "display_query": "山东师范大学学生回宿舍要看 15 秒广告"
  },
  { "query": "新版英语教材被指太难", "display_query": "新版英语教材被指太难" },
  {
    "query": "《崩坏：因缘精灵》开放预约",
    "display_query": "《崩坏：因缘精灵》开放预约"
  },
  {
    "query": "人形机器人乒乓球过招超过100个回合",
    "display_query": "人形机器人乒乓球过招超过100个回合"
  },
  {
    "query": "华为上半年营收 4270 亿元",
    "display_query": "华为上半年营收 4270 亿元"
  },
  {
    "query": "比亚迪上半年营收3713亿元",
    "display_query": "比亚迪上半年营收3713亿元"
  },
  { "query": "曝印尼爆发劳工抗议", "display_query": "曝印尼爆发劳工抗议" }
]
